odoo8_addon_medical_medicament_attributes-8.0.1.0.0.99.dev7-py2.7-nspkg.pth
odoo_addons/medical_medicament_attributes/__openerp__.py
odoo_addons/medical_medicament_attributes/__init__.py
odoo_addons/medical_medicament_attributes/README.rst
odoo_addons/medical_medicament_attributes/security/ir.model.access.csv
odoo_addons/medical_medicament_attributes/models/medical_medicament.py
odoo_addons/medical_medicament_attributes/models/medical_medicament_attribute_flavor.py
odoo_addons/medical_medicament_attributes/models/medical_medicament_attribute_shape.py
odoo_addons/medical_medicament_attributes/models/__init__.py
odoo_addons/medical_medicament_attributes/models/medical_medicament_attribute_color.py
odoo_addons/medical_medicament_attributes/models/medical_medicament_attribute_abstract.py
odoo_addons/medical_medicament_attributes/i18n/pt_BR.po
odoo_addons/medical_medicament_attributes/views/medical_medicament_view.xml
odoo8_addon_medical_medicament_attributes-8.0.1.0.0.99.dev7.dist-info/top_level.txt
odoo8_addon_medical_medicament_attributes-8.0.1.0.0.99.dev7.dist-info/WHEEL
odoo8_addon_medical_medicament_attributes-8.0.1.0.0.99.dev7.dist-info/RECORD
odoo8_addon_medical_medicament_attributes-8.0.1.0.0.99.dev7.dist-info/metadata.json
odoo8_addon_medical_medicament_attributes-8.0.1.0.0.99.dev7.dist-info/DESCRIPTION.rst
odoo8_addon_medical_medicament_attributes-8.0.1.0.0.99.dev7.dist-info/METADATA
odoo8_addon_medical_medicament_attributes-8.0.1.0.0.99.dev7.dist-info/namespace_packages.txt
